sabbath_school_reproducer/__init__.py
sabbath_school_reproducer/aggregator.py
sabbath_school_reproducer/config.py
sabbath_school_reproducer/downloader.py
sabbath_school_reproducer/main.py
sabbath_school_reproducer/processor.py
sabbath_school_reproducer/setup.py
sabbath_school_reproducer/bin/__init__.py
sabbath_school_reproducer/bin/generate_config.py
sabbath_school_reproducer/bin/run.sh
sabbath_school_reproducer/generator/__init__.py
sabbath_school_reproducer/generator/css_editor.py
sabbath_school_reproducer/generator/css_styles.py
sabbath_school_reproducer/generator/html_generator.py
sabbath_school_reproducer/generator/pdf_generator.py
sabbath_school_reproducer/generator/svg_updater.py
sabbath_school_reproducer/utils/__init__.py
sabbath_school_reproducer/utils/debug_tools.py
sabbath_school_reproducer/utils/language_utils.py
sabbath_school_reproducer-0.1.2.data/data/bin/generate_config.py
sabbath_school_reproducer-0.1.2.data/data/bin/run.sh
sabbath_school_reproducer-0.1.2.dist-info/METADATA
sabbath_school_reproducer-0.1.2.dist-info/WHEEL
sabbath_school_reproducer-0.1.2.dist-info/entry_points.txt
sabbath_school_reproducer-0.1.2.dist-info/top_level.txt
sabbath_school_reproducer-0.1.2.dist-info/RECORD
