Metadata-Version: 2.4
Name: sabbath-school-reproducer
Version: 0.1.2
Summary: Download and process Sabbath School lessons from GitHub
Home-page: https://github.com/SabbathSchool/sabbath-school-reproducer
Author: Gospel Sounders
Author-email: youremail@example.com
Classifier: Development Status :: 3 - Alpha
Classifier: Intended Audience :: End Users/Desktop
Classifier: License :: OSI Approved :: MIT License
Classifier: Programming Language :: Python :: 3
Classifier: Programming Language :: Python :: 3.6
Classifier: Programming Language :: Python :: 3.7
Classifier: Programming Language :: Python :: 3.8
Classifier: Programming Language :: Python :: 3.9
Requires-Python: >=3.6
Requires-Dist: pyyaml>=5.1
Requires-Dist: requests>=2.22.0
Requires-Dist: markdown>=3.1.1
Requires-Dist: weasyprint>=51.0
Requires-Dist: beautifulsoup4>=4.8.0
Dynamic: author
Dynamic: author-email
Dynamic: classifier
Dynamic: description
Dynamic: description-content-type
Dynamic: home-page
Dynamic: requires-dist
Dynamic: requires-python
Dynamic: summary
